Open_WiFi/Android.py
Open_WiFi/Linux.py
Open_WiFi/WiFi.py
Open_WiFi/Windows.py
Open_WiFi/__init__.py
Open_WiFi-1.0.dist-info/METADATA
Open_WiFi-1.0.dist-info/WHEEL
Open_WiFi-1.0.dist-info/top_level.txt
Open_WiFi-1.0.dist-info/RECORD
